[
  {
    "id": 80100,
    "date": "2025-09-19 00:25:22+00:00",
    "sender_name": "QUETIAPINUM_BOY",
    "text": "袠斜芯 芯薪 褋褌邪斜懈谢褜薪芯 褉邪蟹 胁 10 褋械泻褍薪写 锌褉芯褌褟卸薪芯 胁蟹写褘褏邪械褌"
  },
  {
    "id": 80099,
    "date": "2025-09-19 00:25:13+00:00",
    "sender_name": "QUETIAPINUM_BOY",
    "text": "携 褋褞泻邪 械写褍 褍谐邪褉邪褞 褋 褝褌芯泄 褏褍泄薪懈"
  },
  {
    "id": 80098,
    "date": "2025-09-19 00:25:04+00:00",
    "sender_name": "QUETIAPINUM_BOY",
    "text": "袣邪泻懈械 褌芯 褕谢褞褏懈 泻褉褍褌褟褌褋褟 锌褉芯褋褌芯 褌懈锌芯 褋褌褉懈锌邪 懈 胁褋褢 锌芯写 褌械褏薪芯"
  },
  {
    "id": 80097,
    "date": "2025-09-19 00:25:01+00:00",
    "sender_name": "QUETIAPINUM_BOY",
    "text": "校 褌邪泻褋懈褋褌邪 薪邪 写懈褋锌谢械械 胁 褌邪泻褋懈"
  },
  {
    "id": 80096,
    "date": "2025-09-19 00:25:01+00:00",
    "sender_name": "QUETIAPINUM_BOY",
    "text": "袦薪械 褌邪泻 泻褉懈薪卸芯胁芯 薪懈泻芯谐写邪 薪械 斜褘谢芯"
  },
  {
    "id": 80095,
    "date": "2025-09-19 00:03:23+00:00",
    "sender_name": "QUETIAPINUM_BOY",
    "text": "10/10"
  },
  {
    "id": 80093,
    "date": "2025-09-18 20:53:15+00:00",
    "sender_name": "oppionme",
    "text": "褝褌芯 锌芯褌芯屑褍 褔褌芯 褟 褍谢褘斜褔懈胁褘泄"
  },
  {
    "id": 80092,
    "date": "2025-09-18 20:53:08+00:00",
    "sender_name": "GeorgeKan",
    "text": "袙芯褌 芯薪 邪蟹邪褉薪懈泻"
  },
  {
    "id": 80091,
    "date": "2025-09-18 20:53:06+00:00",
    "sender_name": "GeorgeKan",
    "text": "袧褍 褌懈锌芯 斜谢褟 胁芯褌 褋械薪褟 锌褉懈泻芯谢懈褋褌 锌芯写 泻芯薪械褑 谢懈屑芯薪邪 蟹邪泻懈薪褍谢"
  },
  {
    "id": 80090,
    "date": "2025-09-18 20:53:01+00:00",
    "sender_name": "oppionme",
    "text": "锌褏胁褏锌褏邪褏邪褏邪褏邪褏褏邪褏邪"
  },
  {
    "id": 80089,
    "date": "2025-09-18 20:52:53+00:00",
    "sender_name": "GeorgeKan",
    "text": "小 褔械谐芯 胁写褉褍谐 褌褘 褉械褕懈谢 械褖械 芯写薪褍 褋泻懈薪褍褌褜 谢邪褋褌芯胁褍褞"
  },
  {
    "id": 80088,
    "date": "2025-09-18 20:52:49+00:00",
    "sender_name": "oppionme",
    "text": "褌懈屑邪 褉褍懈薪邪"
  },
  {
    "id": 80087,
    "date": "2025-09-18 20:52:44+00:00",
    "sender_name": "GeorgeKan",
    "text": "携 褔械褌 胁芯芯褜褖械 薪械 锌芯写褍屑邪谢"
  },
  {
    "id": 80086,
    "date": "2025-09-18 20:52:37+00:00",
    "sender_name": "GeorgeKan",
    "text": "袧褍 褟 械斜谢邪薪"
  },
  {
    "id": 80085,
    "date": "2025-09-18 20:52:35+00:00",
    "sender_name": "oppionme",
    "text": ")))"
  },
  {
    "id": 80084,
    "date": "2025-09-18 20:52:34+00:00",
    "sender_name": "oppionme",
    "text": "薪褍 褟 褋锌械褑懈邪谢褜薪芯 蟹邪屑邪蟹邪谢 锌邪谢褜褑褘"
  },
  {
    "id": 80083,
    "date": "2025-09-18 20:52:28+00:00",
    "sender_name": "GeorgeKan",
    "text": "+ 褑胁械褌"
  },
  {
    "id": 80082,
    "date": "2025-09-18 20:52:25+00:00",
    "sender_name": "GeorgeKan",
    "text": "袙芯褌 锌褉褟屑 斜褍写褌芯 写芯谢卸薪芯 斜胁谢芯 邪 谐芯谢芯胁褍 锌褉懈写褌懈"
  },
  {
    "id": 80081,
    "date": "2025-09-18 20:52:24+00:00",
    "sender_name": "oppionme",
    "text": "@QUETIAPINUM_BOY 芯褑械薪懈胁邪泄 胁褋械 褝褌芯"
  },
  {
    "id": 80080,
    "date": "2025-09-18 20:52:15+00:00",
    "sender_name": "GeorgeKan",
    "text": "袦芯卸薪芯 斜褘谢芯 写芯谐芯写邪褌褜褋褟"
  },
  {
    "id": 80078,
    "date": "2025-09-18 20:52:07+00:00",
    "sender_name": "oppionme",
    "text": "薪械卸写邪薪褍谢"
  },
  {
    "id": 80077,
    "date": "2025-09-18 20:52:05+00:00",
    "sender_name": "oppionme",
    "text": "泻芯薪泻褉械褌薪芯"
  },
  {
    "id": 80076,
    "date": "2025-09-18 20:52:03+00:00",
    "sender_name": "oppionme",
    "text": "邪褏胁褏邪褏胁 薪械卸写邪薪褍褕"
  },
  {
    "id": 80075,
    "date": "2025-09-18 20:51:50+00:00",
    "sender_name": "oppionme",
    "text": "褏邪胁褏邪褏胁褏邪 斜谢褟 写邪"
  },
  {
    "id": 80074,
    "date": "2025-09-18 20:51:47+00:00",
    "sender_name": "GeorgeKan",
    "text": "袧械 谢械屑芯谐"
  },
  {
    "id": 80073,
    "date": "2025-09-18 20:51:42+00:00",
    "sender_name": "oppionme",
    "text": "褏邪邪褏邪褏邪褏褏邪"
  },
  {
    "id": 80072,
    "date": "2025-09-18 20:51:41+00:00",
    "sender_name": "oppionme",
    "text": "啸袗啸袗啸袗啸袗啸袗啸袗啸袗啸袗啸袗啸袗啸袗啸袗啸袗啸袗啸袗啸啸袗袗"
  },
  {
    "id": 80071,
    "date": "2025-09-18 20:51:37+00:00",
    "sender_name": "oppionme",
    "text": "褏邪褏邪褏邪褏邪邪褏褏邪褏邪褏邪褏邪褏邪褏邪褏邪邪"
  },
  {
    "id": 80070,
    "date": "2025-09-18 20:51:35+00:00",
    "sender_name": "GeorgeKan",
    "text": "小褍褔泻邪"
  },
  {
    "id": 80069,
    "date": "2025-09-18 20:51:34+00:00",
    "sender_name": "GeorgeKan",
    "text": "小褍泻邪"
  },
  {
    "id": 80068,
    "date": "2025-09-18 20:51:33+00:00",
    "sender_name": "oppionme",
    "text": "啸袗啸袗啸袗啸袗啸袗啸袗啸袗啸袗啸"
  },
  {
    "id": 80067,
    "date": "2025-09-18 20:51:32+00:00",
    "sender_name": "GeorgeKan",
    "text": "袧械卸写邪薪"
  },
  {
    "id": 80066,
    "date": "2025-09-18 20:51:31+00:00",
    "sender_name": "oppionme",
    "text": "袧袝袞袛袗袧效袠袣"
  },
  {
    "id": 80065,
    "date": "2025-09-18 20:51:31+00:00",
    "sender_name": "GeorgeKan",
    "text": "袘谢褟"
  },
  {
    "id": 80064,
    "date": "2025-09-18 20:51:29+00:00",
    "sender_name": "oppionme",
    "text": "邪褝邪褏邪褏啸袗啸袗啸袗啸袗"
  },
  {
    "id": 80063,
    "date": "2025-09-18 20:51:24+00:00",
    "sender_name": "GeorgeKan",
    "text": "袥懈屑芯薪"
  },
  {
    "id": 80062,
    "date": "2025-09-18 20:51:21+00:00",
    "sender_name": "GeorgeKan",
    "text": "携 锌褉邪胁懈谢褜薪芯 锌芯薪懈屑邪褞 褔褌芯 褟 褖邪褋 褍褔褍褋褜 芯褌谐邪写褘胁邪褌褜 褔褌芯 薪邪 泻邪褉褌懈薪泻械 褋芯 褋锌芯泄谢械褉芯屑 褔褌芯 斜褘 锌芯褌芯屑 薪械 褋泻邪褔懈胁邪褌褜 械褢 懈 薪械 褌褉邪褌懈褌褜 屑械褋褌芯 薪邪 褌械谢械褎芯薪械 邪 褋褉邪蟹褍 胁懈写懈褌褜 褔褌芯 褌邪屑"
  },
  {
    "id": 80061,
    "date": "2025-09-18 20:51:09+00:00",
    "sender_name": "oppionme",
    "text": "薪褍褍 褌懈锌芯"
  },
  {
    "id": 80059,
    "date": "2025-09-18 20:50:17+00:00",
    "sender_name": "GeorgeKan",
    "text": "袠 械褖械 泻邪泻邪褟 褌芯 屑褟褌邪褟 褏褍泄薪褟 褋 蟹邪谐褉褍蟹泻芯泄 锌芯 褑械薪褌褉褍"
  },
  {
    "id": 80058,
    "date": "2025-09-18 20:50:08+00:00",
    "sender_name": "GeorgeKan",
    "text": "袗 褌邪屑 泻谢褍斜薪懈泻邪"
  },
  {
    "id": 80057,
    "date": "2025-09-18 20:50:05+00:00",
    "sender_name": "GeorgeKan",
    "text": "携 写褍屑邪谢 褌褘 谢邪褋褌 泻邪褉褌懈薪泻芯泄 褎谢邪谐 褋泻懈薪褍谢"
  },
  {
    "id": 80056,
    "date": "2025-09-18 20:50:02+00:00",
    "sender_name": "oppionme",
    "text": "谢邪褋褌芯胁邪褟"
  },
  {
    "id": 80055,
    "date": "2025-09-18 20:50:00+00:00",
    "sender_name": "oppionme",
    "text": "褖邪褋"
  },
  {
    "id": 80054,
    "date": "2025-09-18 20:49:52+00:00",
    "sender_name": "oppionme",
    "text": "邪"
  },
  {
    "id": 80053,
    "date": "2025-09-18 20:49:48+00:00",
    "sender_name": "GeorgeKan",
    "text": "携 褔械泻薪褍谢 褍卸械"
  },
  {
    "id": 80052,
    "date": "2025-09-18 20:49:42+00:00",
    "sender_name": "oppionme",
    "text": "芯褌谐邪写邪泄"
  },
  {
    "id": 80050,
    "date": "2025-09-18 20:49:37+00:00",
    "sender_name": "oppionme",
    "text": "锌褉褟屑芯 泻邪泻 褟"
  },
  {
    "id": 80049,
    "date": "2025-09-18 20:49:34+00:00",
    "sender_name": "oppionme",
    "text": "褕懈褉芯泻懈泄 懈 褉芯胁薪褘泄"
  },
  {
    "id": 80048,
    "date": "2025-09-18 20:49:31+00:00",
    "sender_name": "oppionme",
    "text": "褋芯谐谢邪褋械薪"
  },
  {
    "id": 80047,
    "date": "2025-09-18 20:49:31+00:00",
    "sender_name": "GeorgeKan",
    "text": "袧邪 褋芯斜械褋械 褋锌褉芯褋褟褌"
  },
  {
    "id": 80046,
    "date": "2025-09-18 20:49:29+00:00",
    "sender_name": "oppionme",
    "text": "褏锌胁褏锌褏邪褏邪褏邪邪褏邪褏邪褏褏邪邪褏"
  },
  {
    "id": 80045,
    "date": "2025-09-18 20:49:27+00:00",
    "sender_name": "GeorgeKan",
    "text": "袙邪卸薪褘泄 褋泻懈谢谢"
  },
  {
    "id": 80044,
    "date": "2025-09-18 20:49:21+00:00",
    "sender_name": "GeorgeKan",
    "text": "袧邪写芯 斜褘 蟹邪锌芯屑薪懈褌褜 泻邪泻 褎谢邪谐 褟锌芯薪懈懈 蟹邪斜谢斜褉械薪褘泄 胁褘谐谢褟写懈褌"
  },
  {
    "id": 80043,
    "date": "2025-09-18 20:48:57+00:00",
    "sender_name": "oppionme",
    "text": "薪褍 屑薪械 胁锌邪写谢褍 芯斜褉械蟹邪褌褜 斜褘谢芯"
  },
  {
    "id": 80042,
    "date": "2025-09-18 20:48:53+00:00",
    "sender_name": "oppionme",
    "text": "锌芯 褕懈褉懈薪械 锌芯薪褟谢 薪邪胁械褉薪褟泻邪"
  },
  {
    "id": 80041,
    "date": "2025-09-18 20:48:41+00:00",
    "sender_name": "GeorgeKan",
    "text": "袧褍 褌褍褌 褎谢邪谐 褔锌芯薪懈懈"
  },
  {
    "id": 80039,
    "date": "2025-09-18 20:48:29+00:00",
    "sender_name": "GeorgeKan",
    "text": "肖谢邪谐 褟锌芯薪懈懈?"
  },
  {
    "id": 80038,
    "date": "2025-09-18 20:48:26+00:00",
    "sender_name": "GeorgeKan",
    "text": "袗褏锌褏锌褏锌"
  },
  {
    "id": 80035,
    "date": "2025-09-18 20:48:11+00:00",
    "sender_name": "GeorgeKan",
    "text": "携 褋锌邪褌褜 褏芯褔褍"
  },
  {
    "id": 80034,
    "date": "2025-09-18 20:48:09+00:00",
    "sender_name": "GeorgeKan",
    "text": "袥邪写薪芯 谐芯 谢邪褋褌"
  },
  {
    "id": 80033,
    "date": "2025-09-18 20:47:39+00:00",
    "sender_name": "GeorgeKan",
    "text": "袣谢褍斜薪懈泻邪 斜褘谢邪?"
  },
  {
    "id": 80032,
    "date": "2025-09-18 20:47:35+00:00",
    "sender_name": "GeorgeKan",
    "text": "袪芯褌 锌芯褋谢械写谐械械 屑械褋褌芯 泻褍写邪 斜胁 褟 褝褌芯 蟹邪褋褍薪褍谢"
  },
  {
    "id": 80031,
    "date": "2025-09-18 20:47:28+00:00",
    "sender_name": "oppionme",
    "text": "褋锌邪谢懈谢"
  },
  {
    "id": 80030,
    "date": "2025-09-18 20:47:26+00:00",
    "sender_name": "oppionme",
    "text": "芯泄 薪褍 褟"
  },
  {
    "id": 80028,
    "date": "2025-09-18 20:47:19+00:00",
    "sender_name": "oppionme",
    "text": "锌械褔械薪褜械"
  },
  {
    "id": 80027,
    "date": "2025-09-18 20:47:16+00:00",
    "sender_name": "GeorgeKan",
    "text": "效械 锌懈褋邪褌褜"
  },
  {
    "id": 80026,
    "date": "2025-09-18 20:47:14+00:00",
    "sender_name": "GeorgeKan",
    "text": "袠 写芯 褋械褏锌 芯褉 褏蟹"
  },
  {
    "id": 80025,
    "date": "2025-09-18 20:47:11+00:00",
    "sender_name": "GeorgeKan",
    "text": "携 胁芯褌 褖邪褋 褋屑芯褌褉褞"
  },
  {
    "id": 80024,
    "date": "2025-09-18 20:47:07+00:00",
    "sender_name": "GeorgeKan",
    "text": "袧邪 褝褌芯 褘芯褌芯"
  },
  {
    "id": 80023,
    "date": "2025-09-18 20:47:05+00:00",
    "sender_name": "GeorgeKan",
    "text": "效褌芯 褟 写芯谢卸械薪 斜胁谢 薪邪蟹胁邪褌褜"
  },
  {
    "id": 80022,
    "date": "2025-09-18 20:47:01+00:00",
    "sender_name": "GeorgeKan",
    "text": "携 褔械泻薪褍谢 褍卸械"
  },
  {
    "id": 80021,
    "date": "2025-09-18 20:46:54+00:00",
    "sender_name": "oppionme",
    "text": "褝褌芯 胁褘锌械褔泻邪"
  },
  {
    "id": 80020,
    "date": "2025-09-18 20:46:47+00:00",
    "sender_name": "GeorgeKan",
    "text": "袣邪泻芯泄 褌芯 芯褔械褉械写薪芯泄 褌褍锌芯泄 褎褉褍泻褌"
  },
  {
    "id": 80019,
    "date": "2025-09-18 20:46:42+00:00",
    "sender_name": "GeorgeKan",
    "text": "袧械褌 懈写械泄"
  },
  {
    "id": 80018,
    "date": "2025-09-18 20:46:40+00:00",
    "sender_name": "GeorgeKan",
    "text": "啸蟹"
  },
  {
    "id": 80017,
    "date": "2025-09-18 20:46:31+00:00",
    "sender_name": "oppionme",
    "text": "泻芯薪薪械泻褌"
  },
  {
    "id": 80016,
    "date": "2025-09-18 20:46:30+00:00",
    "sender_name": "oppionme",
    "text": "褏邪胁褏邪褏邪褏褏邪"
  },
  {
    "id": 80015,
    "date": "2025-09-18 20:46:27+00:00",
    "sender_name": "oppionme",
    "text": "薪邪 屑邪褌械屑邪褌懈泻械 写褍屑邪褞 屑薪芯谐芯 写邪写褍褌"
  },
  {
    "id": 80014,
    "date": "2025-09-18 20:46:27+00:00",
    "sender_name": "GeorgeKan",
    "text": "袦邪褌懈屑邪褌懈泻邪"
  },
  {
    "id": 80013,
    "date": "2025-09-18 20:46:16+00:00",
    "sender_name": "oppionme",
    "text": "褋屑芯褌褉褟 泻邪泻芯泄 锌褉械写屑械褌"
  },
  {
    "id": 80011,
    "date": "2025-09-18 20:46:01+00:00",
    "sender_name": "GeorgeKan",
    "text": "携斜谢芯泻芯"
  },
  {
    "id": 80010,
    "date": "2025-09-18 20:46:00+00:00",
    "sender_name": "GeorgeKan",
    "text": "袗 薪械褌"
  },
  {
    "id": 80009,
    "date": "2025-09-18 20:45:54+00:00",
    "sender_name": "GeorgeKan",
    "text": "袘械褏械谢懈褌, 芯褔械胁懈写薪芯 卸械"
  },
  {
    "id": 80008,
    "date": "2025-09-18 20:45:44+00:00",
    "sender_name": "GeorgeKan",
    "text": "小泻芯谢褜泻芯 斜邪谢芯胁 写邪写褍褌"
  },
  {
    "id": 80007,
    "date": "2025-09-18 20:45:39+00:00",
    "sender_name": "GeorgeKan",
    "text": "袨褌胁械褔邪褌褜 褎谢邪谐 褟锌芯薪懈懈"
  },
  {
    "id": 80006,
    "date": "2025-09-18 20:45:35+00:00",
    "sender_name": "GeorgeKan",
    "text": "袗 械褋谢懈 薪邪 械谐褝 胁械蟹写械 谐写械 褌褘 薪械 蟹薪邪械褕褜 芯褌胁械褌"
  },
  {
    "id": 80004,
    "date": "2025-09-18 20:45:01+00:00",
    "sender_name": "GeorgeKan",
    "text": "袩邪写褍褕泻邪"
  },
  {
    "id": 80003,
    "date": "2025-09-18 20:44:59+00:00",
    "sender_name": "GeorgeKan",
    "text": "袘褍写褌芯"
  },
  {
    "id": 80002,
    "date": "2025-09-18 20:44:57+00:00",
    "sender_name": "GeorgeKan",
    "text": "协褌芯 泻邪泻邪褟 褌芯 屑褟谐泻邪褟 懈谐褉褍褕泻邪"
  },
  {
    "id": 80001,
    "date": "2025-09-18 20:44:52+00:00",
    "sender_name": "oppionme",
    "text": "锌芯-屑芯械屑褍"
  },
  {
    "id": 80000,
    "date": "2025-09-18 20:44:50+00:00",
    "sender_name": "oppionme",
    "text": "写邪"
  },
  {
    "id": 79999,
    "date": "2025-09-18 20:44:46+00:00",
    "sender_name": "GeorgeKan",
    "text": "协褌芯 褉懈褋褍薪芯泻?"
  },
  {
    "id": 79998,
    "date": "2025-09-18 20:44:43+00:00",
    "sender_name": "GeorgeKan",
    "text": "效褌芯 褝褌芯 蟹邪 褍械斜懈褖薪邪褔 泻邪褉褌懈薪泻邪"
  },
  {
    "id": 79997,
    "date": "2025-09-18 20:44:37+00:00",
    "sender_name": "oppionme",
    "text": "屑褘屑芯"
  },
  {
    "id": 79996,
    "date": "2025-09-18 20:44:30+00:00",
    "sender_name": "GeorgeKan",
    "text": "袩芯屑懈写芯褉"
  },
  {
    "id": 79994,
    "date": "2025-09-18 20:44:06+00:00",
    "sender_name": "GeorgeKan",
    "text": "袧械 褉芯胁薪芯 斜褘谢芯"
  },
  {
    "id": 79993,
    "date": "2025-09-18 20:43:59+00:00",
    "sender_name": "GeorgeKan",
    "text": "袛邪 0 褕邪薪褋芯胁 褍谐邪写邪褌褜 褌邪泻芯械"
  },
  {
    "id": 79992,
    "date": "2025-09-18 20:43:57+00:00",
    "sender_name": "oppionme",
    "text": "邪 褔褢 薪械 褎谢邪谐 携锌芯薪懈懈"
  },
  {
    "id": 79991,
    "date": "2025-09-18 20:43:49+00:00",
    "sender_name": "GeorgeKan",
    "text": "袧褍 褏蟹 锌芯屑懈写芯褉 锌褍褋褌褜 斜褍写械褌"
  },
  {
    "id": 79990,
    "date": "2025-09-18 20:43:35+00:00",
    "sender_name": "oppionme",
    "text": "褝褌芯 谢懈褔懈"
  },
  {
    "id": 79989,
    "date": "2025-09-18 20:43:33+00:00",
    "sender_name": "oppionme",
    "text": "锌褏胁褏邪褏邪"
  },
  {
    "id": 79987,
    "date": "2025-09-18 20:43:10+00:00",
    "sender_name": "GeorgeKan",
    "text": "袩芯 褎芯褌芯"
  },
  {
    "id": 79986,
    "date": "2025-09-18 20:43:08+00:00",
    "sender_name": "GeorgeKan",
    "text": "袧邪写芯 斜褘谢芯 褋褉邪蟹褍 写芯谐芯写邪褌褜褋褟"
  },
  {
    "id": 79985,
    "date": "2025-09-18 20:43:01+00:00",
    "sender_name": "GeorgeKan",
    "text": "孝邪泻 懈 蟹薪邪谢"
  },
  {
    "id": 79984,
    "date": "2025-09-18 20:42:58+00:00",
    "sender_name": "GeorgeKan",
    "text": "协褌芯 褌胁芯泄 谐械屑芯褉芯泄"
  },
  {
    "id": 79983,
    "date": "2025-09-18 20:42:49+00:00",
    "sender_name": "GeorgeKan",
    "text": "携 锌芯薪褟谢"
  },
  {
    "id": 79982,
    "date": "2025-09-18 20:42:47+00:00",
    "sender_name": "GeorgeKan",
    "text": "袗邪邪邪"
  },
  {
    "id": 79981,
    "date": "2025-09-18 20:42:38+00:00",
    "sender_name": "GeorgeKan",
    "text": "袗 褝褌芯 褌芯谐写邪 褔褌芯"
  },
  {
    "id": 79980,
    "date": "2025-09-18 20:42:35+00:00",
    "sender_name": "oppionme",
    "text": "褏邪邪褏褏邪邪. 写褍褉屑邪薪"
  },
  {
    "id": 79979,
    "date": "2025-09-18 20:42:29+00:00",
    "sender_name": "oppionme",
    "text": "芯薪 卸褢谢褌褘泄 蟹械谢褢薪褘泄"
  },
  {
    "id": 79978,
    "date": "2025-09-18 20:42:28+00:00",
    "sender_name": "GeorgeKan",
    "text": "袛邪"
  },
  {
    "id": 79977,
    "date": "2025-09-18 20:42:26+00:00",
    "sender_name": "oppionme",
    "text": "褔褌芯 谢懈"
  },
  {
    "id": 79976,
    "date": "2025-09-18 20:42:24+00:00",
    "sender_name": "GeorgeKan",
    "text": "袗 胁褉械屑褟 褌芯 褕谢芯"
  },
  {
    "id": 79975,
    "date": "2025-09-18 20:42:24+00:00",
    "sender_name": "oppionme",
    "text": "写褍褉懈邪薪"
  },
  {
    "id": 79974,
    "date": "2025-09-18 20:42:20+00:00",
    "sender_name": "GeorgeKan",
    "text": "携 薪械 胁褋锌芯屑薪懈谢 薪邪蟹胁邪薪懈械"
  },
  {
    "id": 79973,
    "date": "2025-09-18 20:42:11+00:00",
    "sender_name": "oppionme",
    "text": "褏邪邪褏邪褏邪褏褏邪褏邪邪"
  },
  {
    "id": 79972,
    "date": "2025-09-18 20:42:09+00:00",
    "sender_name": "oppionme",
    "text": "邪褏邪褏邪褏邪 泻邪泻芯泄 薪邪褏褍泄 写褍褉屑邪薪"
  },
  {
    "id": 79971,
    "date": "2025-09-18 20:41:59+00:00",
    "sender_name": "oppionme",
    "text": "邪褏邪褏褏邪褏邪"
  },
  {
    "id": 79970,
    "date": "2025-09-18 20:41:58+00:00",
    "sender_name": "oppionme",
    "text": "锌芯写谢芯胁懈谢"
  },
  {
    "id": 79969,
    "date": "2025-09-18 20:41:55+00:00",
    "sender_name": "GeorgeKan",
    "text": "袚写械 褌芯 褟 锌褉芯械斜邪谢褋褟"
  },
  {
    "id": 79968,
    "date": "2025-09-18 20:41:50+00:00",
    "sender_name": "GeorgeKan",
    "text": "啸屑"
  },
  {
    "id": 79967,
    "date": "2025-09-18 20:41:49+00:00",
    "sender_name": "oppionme",
    "text": "褏邪褏邪邪褏褏邪褏邪邪"
  },
  {
    "id": 79966,
    "date": "2025-09-18 20:41:47+00:00",
    "sender_name": "GeorgeKan",
    "text": "袛褍褉懈邪薪"
  },
  {
    "id": 79964,
    "date": "2025-09-18 20:41:33+00:00",
    "sender_name": "GeorgeKan",
    "text": "肖谢邪谐 褟锌芯薪懈懈"
  },
  {
    "id": 79962,
    "date": "2025-09-18 20:41:10+00:00",
    "sender_name": "GeorgeKan",
    "text": "袧邪 写械薪褜谐懈"
  },
  {
    "id": 79961,
    "date": "2025-09-18 20:41:06+00:00",
    "sender_name": "GeorgeKan",
    "text": "协褌芯 褋泻邪屑 械斜褍褔懈泄"
  },
  {
    "id": 79960,
    "date": "2025-09-18 20:41:03+00:00",
    "sender_name": "GeorgeKan",
    "text": "袙芯褌 锌褉褟屑 褔械褌泻芯械 褟斜谢芯泻芯"
  },
  {
    "id": 79959,
    "date": "2025-09-18 20:40:59+00:00",
    "sender_name": "GeorgeKan",
    "text": "袣邪泻 褍 褟斜谢芯泻邪"
  },
  {
    "id": 79958,
    "date": "2025-09-18 20:40:55+00:00",
    "sender_name": "GeorgeKan",
    "text": "孝邪屑 斜褘谢芯 褔褌芯 褌芯 褌懈锌芯 胁械褌芯褔泻懈"
  },
  {
    "id": 79957,
    "date": "2025-09-18 20:40:54+00:00",
    "sender_name": "oppionme",
    "text": "褍褋芯屑薪懈褋褜"
  },
  {
    "id": 79956,
    "date": "2025-09-18 20:40:52+00:00",
    "sender_name": "oppionme",
    "text": "褏褍褏褍褏褍邪褏褏邪褏邪褏"
  },
  {
    "id": 79955,
    "date": "2025-09-18 20:40:49+00:00",
    "sender_name": "GeorgeKan",
    "text": "袧褍 泻邪泻"
  },
  {
    "id": 79954,
    "date": "2025-09-18 20:40:48+00:00",
    "sender_name": "GeorgeKan",
    "text": "袛邪 斜谢褟褌褜"
  },
  {
    "id": 79953,
    "date": "2025-09-18 20:40:44+00:00",
    "sender_name": "GeorgeKan",
    "text": "袧邪 100%"
  },
  {
    "id": 79952,
    "date": "2025-09-18 20:40:41+00:00",
    "sender_name": "GeorgeKan",
    "text": "校胁械褉械薪"
  },
  {
    "id": 79951,
    "date": "2025-09-18 20:40:40+00:00",
    "sender_name": "GeorgeKan",
    "text": "携斜谢芯泻芯"
  },
  {
    "id": 79949,
    "date": "2025-09-18 20:40:19+00:00",
    "sender_name": "GeorgeKan",
    "text": "袧械褌褍 褌邪泻懈褏 褎褉褍泻褌芯胁"
  },
  {
    "id": 79948,
    "date": "2025-09-18 20:40:16+00:00",
    "sender_name": "GeorgeKan",
    "text": "啸蟹"
  },
  {
    "id": 79947,
    "date": "2025-09-18 20:40:15+00:00",
    "sender_name": "GeorgeKan",
    "text": "袣邪泻邪褟 褌芯 褏褍泄薪, 褋 泻褉邪褋薪褘屑 胁械褉褏芯屑"
  },
  {
    "id": 79946,
    "date": "2025-09-18 20:40:05+00:00",
    "sender_name": "oppionme",
    "text": "蟹薪邪褔懈褌 褝褌芯 邪薪邪薪邪褋"
  },
  {
    "id": 79945,
    "date": "2025-09-18 20:39:58+00:00",
    "sender_name": "GeorgeKan",
    "text": "携 薪械 褋械泻褍薪写褘 薪械 褋芯屑薪懈胁邪谢褋褟 胁 褌芯屑 褔褌芯 褝褌芯 邪薪邪薪邪褋"
  },
  {
    "id": 79944,
    "date": "2025-09-18 20:39:51+00:00",
    "sender_name": "oppionme",
    "text": "薪邪写芯 斜褘谢芯 褍褋芯屑薪懈褌褋褟 薪械屑薪芯谐芯"
  },
  {
    "id": 79943,
    "date": "2025-09-18 20:39:45+00:00",
    "sender_name": "oppionme",
    "text": "褟 褍 褌械斜褟 褋锌褉邪褕懈胁邪褞 屑薪械 褉邪蟹褉械褕邪械褌 懈谢懈 薪械褌"
  },
  {
    "id": 79942,
    "date": "2025-09-18 20:39:43+00:00",
    "sender_name": "GeorgeKan",
    "text": "袧邪 100%"
  },
  {
    "id": 79941,
    "date": "2025-09-18 20:39:41+00:00",
    "sender_name": "GeorgeKan",
    "text": "携 锌褉褟屑 褍胁械褉械谐 斜褘谢"
  },
  {
    "id": 79940,
    "date": "2025-09-18 20:39:36+00:00",
    "sender_name": "GeorgeKan",
    "text": "袘谢褟 邪 泻邪泻 薪械 邪薪邪薪邪褋 褌芯"
  },
  {
    "id": 79938,
    "date": "2025-09-18 20:39:26+00:00",
    "sender_name": "oppionme",
    "text": "褔褝褘褏邪褏邪褏"
  },
  {
    "id": 79937,
    "date": "2025-09-18 20:39:26+00:00",
    "sender_name": "GeorgeKan",
    "text": "袘芯谐 褟胁薪芯 薪械 芯写芯斜褉懈褌"
  },
  {
    "id": 79936,
    "date": "2025-09-18 20:39:21+00:00",
    "sender_name": "GeorgeKan",
    "text": "袠谢懈 褋 褉械谢懈谐懈芯蟹薪芯泄"
  },
  {
    "id": 79935,
    "date": "2025-09-18 20:39:17+00:00",
    "sender_name": "GeorgeKan",
    "text": "孝褘 褋锌褉邪褕懈胁邪械褕褜 褋 屑芯褉邪谢褜薪芯泄 褌芯褔泻懈 蟹褉械薪懈褟?"
  }
]