[
  {
    "id": 115419,
    "date": "2025-11-09 19:54:09+00:00",
    "sender_name": "GeorgeKan",
    "text": "Ну этот"
  },
  {
    "id": 115418,
    "date": "2025-11-09 19:54:04+00:00",
    "sender_name": "gaysesg",
    "text": "Не смешной"
  },
  {
    "id": 115417,
    "date": "2025-11-09 19:54:02+00:00",
    "sender_name": "selfrapevictimbitchassnigga",
    "text": "Какой"
  },
  {
    "id": 115416,
    "date": "2025-11-09 19:53:51+00:00",
    "sender_name": "GeorgeKan",
    "text": "Рома оцени смешной кружок"
  },
  {
    "id": 115415,
    "date": "2025-11-09 19:53:50+00:00",
    "sender_name": "QUETIAPINUM_BOY",
    "text": "Жирная"
  },
  {
    "id": 115414,
    "date": "2025-11-09 19:53:49+00:00",
    "sender_name": "QUETIAPINUM_BOY",
    "text": "Сука"
  },
  {
    "id": 115413,
    "date": "2025-11-09 19:53:48+00:00",
    "sender_name": "oppionme",
    "text": "ливай"
  },
  {
    "id": 115412,
    "date": "2025-11-09 19:53:48+00:00",
    "sender_name": "QUETIAPINUM_BOY",
    "text": "Толстая"
  },
  {
    "id": 115411,
    "date": "2025-11-09 19:53:46+00:00",
    "sender_name": "QUETIAPINUM_BOY",
    "text": "Не в лазите"
  },
  {
    "id": 115410,
    "date": "2025-11-09 19:53:44+00:00",
    "sender_name": "QUETIAPINUM_BOY",
    "text": "Толстая мамаша Хрюндель"
  },
  {
    "id": 115409,
    "date": "2025-11-09 19:53:37+00:00",
    "sender_name": "oppionme",
    "text": "это правда"
  },
  {
    "id": 115408,
    "date": "2025-11-09 19:53:35+00:00",
    "sender_name": "selfrapevictimbitchassnigga",
    "text": "Лан пацаны давайте"
  },
  {
    "id": 115407,
    "date": "2025-11-09 19:53:32+00:00",
    "sender_name": "selfrapevictimbitchassnigga",
    "text": "571 Кто-то написал"
  },
  {
    "id": 115406,
    "date": "2025-11-09 19:53:29+00:00",
    "sender_name": "selfrapevictimbitchassnigga",
    "text": "Фух я думал выше лимита"
  },
  {
    "id": 115405,
    "date": "2025-11-09 19:53:24+00:00",
    "sender_name": "selfrapevictimbitchassnigga",
    "text": "Базар"
  },
  {
    "id": 115404,
    "date": "2025-11-09 19:53:15+00:00",
    "sender_name": "GeorgeKan",
    "text": "Максимум 570"
  },
  {
    "id": 115403,
    "date": "2025-11-09 19:53:08+00:00",
    "sender_name": "GeorgeKan",
    "text": "Честно"
  },
  {
    "id": 115402,
    "date": "2025-11-09 19:53:06+00:00",
    "sender_name": "GeorgeKan",
    "text": "Тут не все 600 сообщений про твоб толстую маму"
  },
  {
    "id": 115400,
    "date": "2025-11-09 19:52:57+00:00",
    "sender_name": "GeorgeKan",
    "text": "Так совпало просто"
  },
  {
    "id": 115399,
    "date": "2025-11-09 19:52:46+00:00",
    "sender_name": "selfrapevictimbitchassnigga",
    "text": "Это то что моя мамка толстая"
  },
  {
    "id": 115398,
    "date": "2025-11-09 19:52:42+00:00",
    "sender_name": "selfrapevictimbitchassnigga",
    "text": "И буквально первое сообщение что у меня прогружается"
  },
  {
    "id": 115397,
    "date": "2025-11-09 19:52:35+00:00",
    "sender_name": "selfrapevictimbitchassnigga",
    "text": "Захожу в чат чтобы скинуть 600 уведов"
  },
  {
    "id": 115396,
    "date": "2025-11-09 19:52:29+00:00",
    "sender_name": "selfrapevictimbitchassnigga",
    "text": "Сижу"
  },
  {
    "id": 115395,
    "date": "2025-11-09 19:52:27+00:00",
    "sender_name": "selfrapevictimbitchassnigga",
    "text": "Я просто"
  },
  {
    "id": 115394,
    "date": "2025-11-09 19:52:26+00:00",
    "sender_name": "selfrapevictimbitchassnigga",
    "text": "Нет"
  },
  {
    "id": 115393,
    "date": "2025-11-09 19:51:37+00:00",
    "sender_name": "oppionme",
    "text": "ты реально чат читаешь что ли дебик"
  },
  {
    "id": 115392,
    "date": "2025-11-09 19:48:56+00:00",
    "sender_name": "GeorgeKan",
    "text": "Не борщи"
  },
  {
    "id": 115391,
    "date": "2025-11-09 19:48:53+00:00",
    "sender_name": "GeorgeKan",
    "text": "Не ну ты тоже границы то знай"
  },
  {
    "id": 115390,
    "date": "2025-11-09 19:43:29+00:00",
    "sender_name": "selfrapevictimbitchassnigga",
    "text": "Гей"
  },
  {
    "id": 115389,
    "date": "2025-11-09 19:43:28+00:00",
    "sender_name": "selfrapevictimbitchassnigga",
    "text": "Чмо"
  },
  {
    "id": 115388,
    "date": "2025-11-09 19:43:27+00:00",
    "sender_name": "selfrapevictimbitchassnigga",
    "text": "Я же твой баребух тебя же жрать заставлю"
  },
  {
    "id": 115387,
    "date": "2025-11-09 19:43:08+00:00",
    "sender_name": "selfrapevictimbitchassnigga",
    "text": "Я же тебя найду"
  },
  {
    "id": 115386,
    "date": "2025-11-09 19:43:05+00:00",
    "sender_name": "selfrapevictimbitchassnigga",
    "text": "Ты долбоеб?"
  },
  {
    "id": 115385,
    "date": "2025-11-09 19:41:42+00:00",
    "sender_name": "QUETIAPINUM_BOY",
    "text": "Да"
  },
  {
    "id": 115384,
    "date": "2025-11-09 19:40:33+00:00",
    "sender_name": "oppionme",
    "text": "Да"
  },
  {
    "id": 115383,
    "date": "2025-11-09 19:33:19+00:00",
    "sender_name": "GeorgeKan",
    "text": "Да"
  },
  {
    "id": 115382,
    "date": "2025-11-09 19:33:04+00:00",
    "sender_name": "gaysesg",
    "text": "Описание правда?"
  },
  {
    "id": 115381,
    "date": "2025-11-09 19:31:39+00:00",
    "sender_name": "oppionme",
    "text": "пидорас плати"
  },
  {
    "id": 115380,
    "date": "2025-11-09 19:26:59+00:00",
    "sender_name": "GeorgeKan",
    "text": "Ты ахуел"
  },
  {
    "id": 115379,
    "date": "2025-11-09 19:26:56+00:00",
    "sender_name": "GeorgeKan",
    "text": "Я за каждое такое сообщение по 7 рублей платил"
  },
  {
    "id": 115378,
    "date": "2025-11-09 19:26:34+00:00",
    "sender_name": "QUETIAPINUM_BOY",
    "text": "Ты щас будешь принимать мой хуй себе в рот"
  },
  {
    "id": 115377,
    "date": "2025-11-09 19:26:10+00:00",
    "sender_name": "GeorgeKan",
    "text": "Ты 1 должен платить"
  },
  {
    "id": 115376,
    "date": "2025-11-09 19:26:03+00:00",
    "sender_name": "GeorgeKan",
    "text": "Ты больше всех пишешь хуйню"
  },
  {
    "id": 115375,
    "date": "2025-11-09 19:25:55+00:00",
    "sender_name": "GeorgeKan",
    "text": "Не смеши"
  },
  {
    "id": 115374,
    "date": "2025-11-09 19:25:54+00:00",
    "sender_name": "QUETIAPINUM_BOY",
    "text": "Объективе"
  },
  {
    "id": 115373,
    "date": "2025-11-09 19:25:53+00:00",
    "sender_name": "GeorgeKan",
    "text": "Апхпхпхп"
  },
  {
    "id": 115372,
    "date": "2025-11-09 19:25:52+00:00",
    "sender_name": "QUETIAPINUM_BOY",
    "text": "Мне можно не платить"
  },
  {
    "id": 115371,
    "date": "2025-11-09 19:25:49+00:00",
    "sender_name": "QUETIAPINUM_BOY",
    "text": "Хуйню"
  },
  {
    "id": 115370,
    "date": "2025-11-09 19:25:49+00:00",
    "sender_name": "GeorgeKan",
    "text": "Ты схуяли решил что можешь не платить"
  },
  {
    "id": 115369,
    "date": "2025-11-09 19:25:47+00:00",
    "sender_name": "QUETIAPINUM_BOY",
    "text": "Я меньше всех пишу"
  },
  {
    "id": 115368,
    "date": "2025-11-09 19:25:41+00:00",
    "sender_name": "GeorgeKan",
    "text": "Ты ахуел"
  },
  {
    "id": 115367,
    "date": "2025-11-09 19:25:39+00:00",
    "sender_name": "GeorgeKan",
    "text": "Тимоха"
  },
  {
    "id": 115366,
    "date": "2025-11-09 19:25:34+00:00",
    "sender_name": "oppionme",
    "text": "ебанат плати по счетам"
  },
  {
    "id": 115365,
    "date": "2025-11-09 19:25:29+00:00",
    "sender_name": "oppionme",
    "text": "мы за него доплачивали похожу все это время"
  },
  {
    "id": 115364,
    "date": "2025-11-09 19:25:25+00:00",
    "sender_name": "GeorgeKan",
    "text": "Я ежемесично отпровляю деньги"
  },
  {
    "id": 115363,
    "date": "2025-11-09 19:25:22+00:00",
    "sender_name": "oppionme",
    "text": "ебаный Тимофей"
  },
  {
    "id": 115362,
    "date": "2025-11-09 19:25:19+00:00",
    "sender_name": "GeorgeKan",
    "text": "Где бабки"
  },
  {
    "id": 115361,
    "date": "2025-11-09 19:25:16+00:00",
    "sender_name": "GeorgeKan",
    "text": "Уёбок"
  },
  {
    "id": 115360,
    "date": "2025-11-09 19:25:15+00:00",
    "sender_name": "GeorgeKan",
    "text": "Не скидываешся"
  },
  {
    "id": 115359,
    "date": "2025-11-09 19:25:11+00:00",
    "sender_name": "GeorgeKan",
    "text": "Ты че"
  },
  {
    "id": 115358,
    "date": "2025-11-09 19:25:10+00:00",
    "sender_name": "GeorgeKan",
    "text": "Так мы и платим"
  },
  {
    "id": 115357,
    "date": "2025-11-09 19:25:07+00:00",
    "sender_name": "oppionme",
    "text": "это туалет для сообщений"
  },
  {
    "id": 115356,
    "date": "2025-11-09 19:25:01+00:00",
    "sender_name": "oppionme",
    "text": "Дрочка неизбежна"
  },
  {
    "id": 115354,
    "date": "2025-11-09 19:24:44+00:00",
    "sender_name": "GeorgeKan",
    "text": "Есть стояк"
  },
  {
    "id": 115353,
    "date": "2025-11-09 19:24:42+00:00",
    "sender_name": "GeorgeKan",
    "text": "И там у раковины"
  },
  {
    "id": 115352,
    "date": "2025-11-09 19:24:39+00:00",
    "sender_name": "GeorgeKan",
    "text": "А если ты просто зашел в ванну"
  },
  {
    "id": 115350,
    "date": "2025-11-09 19:24:15+00:00",
    "sender_name": "oppionme",
    "text": "Запомните: \nЕсли в одной комнате два стояка - значит секс неизбежен."
  },
  {
    "id": 115349,
    "date": "2025-11-09 19:23:43+00:00",
    "sender_name": "oppionme",
    "text": "Жора у меня щас тоже в таком случае встанет"
  },
  {
    "id": 115348,
    "date": "2025-11-09 19:23:27+00:00",
    "sender_name": "oppionme",
    "text": "фак"
  },
  {
    "id": 115347,
    "date": "2025-11-09 19:23:01+00:00",
    "sender_name": "GeorgeKan",
    "text": "Это любой твой кружок"
  },
  {
    "id": 115346,
    "date": "2025-11-09 19:22:42+00:00",
    "sender_name": "oppionme",
    "text": "я щас скину кружок тебе в ЛС где я слишком сексуален для того что бы у тебя не встал"
  },
  {
    "id": 115345,
    "date": "2025-11-09 19:21:44+00:00",
    "sender_name": "GeorgeKan",
    "text": "Ты пупсень"
  },
  {
    "id": 115344,
    "date": "2025-11-09 19:21:29+00:00",
    "sender_name": "oppionme",
    "text": "а как же вупсень"
  },
  {
    "id": 115343,
    "date": "2025-11-09 19:17:06+00:00",
    "sender_name": "GeorgeKan",
    "text": "Храмуля чёткий тип"
  },
  {
    "id": 115342,
    "date": "2025-11-09 19:16:57+00:00",
    "sender_name": "GeorgeKan",
    "text": "Псих крысёныш"
  },
  {
    "id": 115341,
    "date": "2025-11-09 19:16:44+00:00",
    "sender_name": "GeorgeKan",
    "text": "Димас продакшен еблан"
  },
  {
    "id": 115340,
    "date": "2025-11-09 19:16:39+00:00",
    "sender_name": "GeorgeKan",
    "text": "Что бы понять что физрук лох"
  },
  {
    "id": 115339,
    "date": "2025-11-09 19:16:32+00:00",
    "sender_name": "QUETIAPINUM_BOY",
    "text": "Уроды ебаные"
  },
  {
    "id": 115338,
    "date": "2025-11-09 19:16:25+00:00",
    "sender_name": "GeorgeKan",
    "text": "Посмотри физрука"
  },
  {
    "id": 115337,
    "date": "2025-11-09 19:16:20+00:00",
    "sender_name": "gaysesg",
    "text": "и поймешь"
  },
  {
    "id": 115336,
    "date": "2025-11-09 19:16:19+00:00",
    "sender_name": "gaysesg",
    "text": "так ты посмотри"
  },
  {
    "id": 115335,
    "date": "2025-11-09 19:16:13+00:00",
    "sender_name": "oppionme",
    "text": "специально"
  },
  {
    "id": 115334,
    "date": "2025-11-09 19:16:10+00:00",
    "sender_name": "oppionme",
    "text": "просто что бы мы ни хуя не понимали"
  },
  {
    "id": 115333,
    "date": "2025-11-09 19:16:06+00:00",
    "sender_name": "oppionme",
    "text": "ну они реально хуцню будут обсуждать два часа"
  },
  {
    "id": 115332,
    "date": "2025-11-09 19:15:46+00:00",
    "sender_name": "GeorgeKan",
    "text": "Тем более тимоха ты усач"
  },
  {
    "id": 115331,
    "date": "2025-11-09 19:15:40+00:00",
    "sender_name": "GeorgeKan",
    "text": "Пойдёт"
  },
  {
    "id": 115330,
    "date": "2025-11-09 19:15:37+00:00",
    "sender_name": "GeorgeKan",
    "text": "Но с серегой норм"
  },
  {
    "id": 115329,
    "date": "2025-11-09 19:15:33+00:00",
    "sender_name": "GeorgeKan",
    "text": "Просто чистейший понос из жопы"
  },
  {
    "id": 115328,
    "date": "2025-11-09 19:15:28+00:00",
    "sender_name": "GeorgeKan",
    "text": "Сирик как и все остальные полнейшая залупа"
  },
  {
    "id": 115327,
    "date": "2025-11-09 19:15:21+00:00",
    "sender_name": "GeorgeKan",
    "text": "Просто так само собой смотреть физрука хуцня"
  },
  {
    "id": 115326,
    "date": "2025-11-09 19:15:14+00:00",
    "sender_name": "GeorgeKan",
    "text": "С серегой норм"
  },
  {
    "id": 115325,
    "date": "2025-11-09 19:15:05+00:00",
    "sender_name": "GeorgeKan",
    "text": "Нет"
  },
  {
    "id": 115324,
    "date": "2025-11-09 19:15:01+00:00",
    "sender_name": "gaysesg",
    "text": "сними собаку с хуя"
  },
  {
    "id": 115323,
    "date": "2025-11-09 19:15:01+00:00",
    "sender_name": "GeorgeKan",
    "text": "Почему"
  },
  {
    "id": 115320,
    "date": "2025-11-09 19:14:04+00:00",
    "sender_name": "gaysesg",
    "text": "посмотри физрука"
  },
  {
    "id": 115319,
    "date": "2025-11-09 19:14:01+00:00",
    "sender_name": "gaysesg",
    "text": "тимоха что бы понять почему ты усач"
  },
  {
    "id": 115317,
    "date": "2025-11-09 19:13:45+00:00",
    "sender_name": "oppionme",
    "text": "стопроцентно"
  },
  {
    "id": 115316,
    "date": "2025-11-09 19:13:40+00:00",
    "sender_name": "gaysesg",
    "text": "физрука посмотри"
  },
  {
    "id": 115315,
    "date": "2025-11-09 19:13:38+00:00",
    "sender_name": "QUETIAPINUM_BOY",
    "text": "Ну потому что он лопнул"
  },
  {
    "id": 115314,
    "date": "2025-11-09 19:13:36+00:00",
    "sender_name": "gaysesg",
    "text": "физрука посмотри"
  },
  {
    "id": 115313,
    "date": "2025-11-09 19:13:33+00:00",
    "sender_name": "QUETIAPINUM_BOY",
    "text": "Выздоравливай"
  },
  {
    "id": 115312,
    "date": "2025-11-09 19:13:32+00:00",
    "sender_name": "oppionme",
    "text": "геморрой прошел давным давно"
  },
  {
    "id": 115311,
    "date": "2025-11-09 19:13:25+00:00",
    "sender_name": "oppionme",
    "text": "болею бро"
  },
  {
    "id": 115310,
    "date": "2025-11-09 19:13:21+00:00",
    "sender_name": "QUETIAPINUM_BOY",
    "text": "Геморрой лопнул?"
  },
  {
    "id": 115309,
    "date": "2025-11-09 19:13:20+00:00",
    "sender_name": "oppionme",
    "text": "завтра чекну"
  },
  {
    "id": 115308,
    "date": "2025-11-09 19:13:18+00:00",
    "sender_name": "oppionme",
    "text": "а не неинтересно"
  },
  {
    "id": 115307,
    "date": "2025-11-09 19:13:15+00:00",
    "sender_name": "oppionme",
    "text": "ты тупрая у меня день хуевый"
  },
  {
    "id": 115306,
    "date": "2025-11-09 19:13:06+00:00",
    "sender_name": "QUETIAPINUM_BOY",
    "text": "Забудь тогда"
  },
  {
    "id": 115305,
    "date": "2025-11-09 19:13:04+00:00",
    "sender_name": "QUETIAPINUM_BOY",
    "text": "не особо смешно"
  },
  {
    "id": 115304,
    "date": "2025-11-09 19:13:02+00:00",
    "sender_name": "oppionme",
    "text": "согл"
  },
  {
    "id": 115303,
    "date": "2025-11-09 19:13:01+00:00",
    "sender_name": "QUETIAPINUM_BOY",
    "text": "Но если тебе не интересно то позуйтам"
  },
  {
    "id": 115302,
    "date": "2025-11-09 19:12:56+00:00",
    "sender_name": "QUETIAPINUM_BOY",
    "text": "АРСЕЕИЙ если на вайбе смотри кружок"
  },
  {
    "id": 115301,
    "date": "2025-11-09 19:12:44+00:00",
    "sender_name": "GeorgeKan",
    "text": "Это фулл ник"
  },
  {
    "id": 115300,
    "date": "2025-11-09 19:12:40+00:00",
    "sender_name": "GeorgeKan",
    "text": "Серега долбаеб"
  },
  {
    "id": 115299,
    "date": "2025-11-09 19:12:31+00:00",
    "sender_name": "oppionme",
    "text": "долбоеб"
  },
  {
    "id": 115298,
    "date": "2025-11-09 19:12:26+00:00",
    "sender_name": "GeorgeKan",
    "text": "Но все ровно тупой"
  },
  {
    "id": 115297,
    "date": "2025-11-09 19:12:26+00:00",
    "sender_name": "QUETIAPINUM_BOY",
    "text": "ВЫ ЖЕ НАМЕРЕННО ДЛЯ ТРОЛЛИНГА МЕНЯ ЩАС БУДЕТЕ ХУЙНЮ ОБСУЖДАТЬ ДВА ЧАСА"
  },
  {
    "id": 115296,
    "date": "2025-11-09 19:12:17+00:00",
    "sender_name": "GeorgeKan",
    "text": "Тоже верно"
  },
  {
    "id": 115295,
    "date": "2025-11-09 19:12:17+00:00",
    "sender_name": "QUETIAPINUM_BOY",
    "text": "ВЫ ЕБНУТЫЕ"
  },
  {
    "id": 115294,
    "date": "2025-11-09 19:12:08+00:00",
    "sender_name": "gaysesg",
    "text": "че тупой то"
  },
  {
    "id": 115293,
    "date": "2025-11-09 19:12:05+00:00",
    "sender_name": "gaysesg",
    "text": "школьницу жирную потрахал и пожил на ее бабки"
  },
  {
    "id": 115292,
    "date": "2025-11-09 19:11:53+00:00",
    "sender_name": "GeorgeKan",
    "text": "На выдачу или на приём?"
  },
  {
    "id": 115291,
    "date": "2025-11-09 19:11:51+00:00",
    "sender_name": "gaysesg",
    "text": "ну димас че"
  },
  {
    "id": 115289,
    "date": "2025-11-09 19:11:38+00:00",
    "sender_name": "QUETIAPINUM_BOY",
    "text": "Сорри"
  },
  {
    "id": 115288,
    "date": "2025-11-09 19:11:36+00:00",
    "sender_name": "QUETIAPINUM_BOY",
    "text": "Жора ты опять проебал"
  },
  {
    "id": 115287,
    "date": "2025-11-09 19:11:28+00:00",
    "sender_name": "GeorgeKan",
    "text": "То димас просто наитупейший еблан"
  },
  {
    "id": 115286,
    "date": "2025-11-09 19:11:21+00:00",
    "sender_name": "GeorgeKan",
    "text": "Если фома просто лох"
  },
  {
    "id": 115285,
    "date": "2025-11-09 19:11:18+00:00",
    "sender_name": "QUETIAPINUM_BOY",
    "text": "Нижний комментарий не имеет права ебаться в очко два года"
  },
  {
    "id": 115284,
    "date": "2025-11-09 19:11:12+00:00",
    "sender_name": "GeorgeKan",
    "text": "Прям нереально тупой"
  },
  {
    "id": 115283,
    "date": "2025-11-09 19:11:08+00:00",
    "sender_name": "GeorgeKan",
    "text": "Димас прожакшен тоже тупой"
  },
  {
    "id": 115282,
    "date": "2025-11-09 19:11:05+00:00",
    "sender_name": "QUETIAPINUM_BOY",
    "text": "🤫🤫🤫"
  },
  {
    "id": 115281,
    "date": "2025-11-09 19:10:54+00:00",
    "sender_name": "gaysesg",
    "text": "тимоха ты усач"
  },
  {
    "id": 115280,
    "date": "2025-11-09 19:10:51+00:00",
    "sender_name": "GeorgeKan",
    "text": "Ты шизик"
  },
  {
    "id": 115279,
    "date": "2025-11-09 19:10:47+00:00",
    "sender_name": "GeorgeKan",
    "text": "Знаешь че?"
  },
  {
    "id": 115278,
    "date": "2025-11-09 19:10:44+00:00",
    "sender_name": "GeorgeKan",
    "text": "Тимох"
  },
  {
    "id": 115277,
    "date": "2025-11-09 19:10:30+00:00",
    "sender_name": "GeorgeKan",
    "text": "..."
  },
  {
    "id": 115276,
    "date": "2025-11-09 19:10:29+00:00",
    "sender_name": "GeorgeKan",
    "text": "Будем"
  },
  {
    "id": 115275,
    "date": "2025-11-09 19:10:16+00:00",
    "sender_name": "GeorgeKan",
    "text": "Серега"
  },
  {
    "id": 115274,
    "date": "2025-11-09 19:09:57+00:00",
    "sender_name": "gaysesg",
    "text": "серега"
  },
  {
    "id": 115273,
    "date": "2025-11-09 19:09:55+00:00",
    "sender_name": "QUETIAPINUM_BOY",
    "text": "КАКОЦ НАХУЙ СЕРЕГА"
  },
  {
    "id": 115272,
    "date": "2025-11-09 19:09:52+00:00",
    "sender_name": "QUETIAPINUM_BOY",
    "text": "Какой нахуй серега"
  },
  {
    "id": 115271,
    "date": "2025-11-09 19:09:46+00:00",
    "sender_name": "gaysesg",
    "text": "а серега смотрел слово пацана?"
  },
  {
    "id": 115269,
    "date": "2025-11-09 19:08:31+00:00",
    "sender_name": "GeorgeKan",
    "text": "Не ну фома реально лохозавр"
  },
  {
    "id": 115268,
    "date": "2025-11-09 19:00:39+00:00",
    "sender_name": "GeorgeKan",
    "text": "Потому что он бегает как шнырь курьер весь сезон"
  },
  {
    "id": 115267,
    "date": "2025-11-09 19:00:21+00:00",
    "sender_name": "gaysesg",
    "text": "почему"
  },
  {
    "id": 115266,
    "date": "2025-11-09 19:00:15+00:00",
    "sender_name": "GeorgeKan",
    "text": "Ебучий лохозавр на физруке"
  },
  {
    "id": 115265,
    "date": "2025-11-09 19:00:10+00:00",
    "sender_name": "GeorgeKan",
    "text": "Смотрю"
  },
  {
    "id": 115264,
    "date": "2025-11-09 19:00:08+00:00",
    "sender_name": "GeorgeKan",
    "text": "Ты"
  },
  {
    "id": 115263,
    "date": "2025-11-09 19:00:06+00:00",
    "sender_name": "gaysesg",
    "text": "смотри"
  },
  {
    "id": 115262,
    "date": "2025-11-09 19:00:05+00:00",
    "sender_name": "gaysesg",
    "text": "ты сучка"
  }
]