[
  {
    "id": 24495,
    "date": "2025-06-24 19:28:46+00:00",
    "sender_name": "bfcrazy",
    "text": "Не потяну популярность"
  },
  {
    "id": 24494,
    "date": "2025-06-24 19:28:40+00:00",
    "sender_name": "bfcrazy",
    "text": "Ну он слишком крутй"
  },
  {
    "id": 24493,
    "date": "2025-06-24 19:28:37+00:00",
    "sender_name": "bfcrazy",
    "text": "Понял"
  },
  {
    "id": 24492,
    "date": "2025-06-24 19:28:32+00:00",
    "sender_name": "GeorgeKan",
    "text": "Имба потому что"
  },
  {
    "id": 24491,
    "date": "2025-06-24 19:28:25+00:00",
    "sender_name": "bfcrazy",
    "text": "Ты нахуя это в буфере обмена держишь"
  },
  {
    "id": 24490,
    "date": "2025-06-24 19:28:13+00:00",
    "sender_name": "GeorgeKan",
    "text": "Deadly Parkour Killer Dark Brawl Stars Assassin Stalker Sniper 1998rus"
  },
  {
    "id": 24489,
    "date": "2025-06-24 19:28:04+00:00",
    "sender_name": "bfcrazy",
    "text": "Самый крутой возьму"
  },
  {
    "id": 24488,
    "date": "2025-06-24 19:28:01+00:00",
    "sender_name": "bfcrazy",
    "text": "Кстати после дембеля думайте мне новый никнейм"
  },
  {
    "id": 24487,
    "date": "2025-06-24 19:27:32+00:00",
    "sender_name": "bfcrazy",
    "text": "Че"
  },
  {
    "id": 24486,
    "date": "2025-06-24 19:27:31+00:00",
    "sender_name": "bfcrazy",
    "text": "Яе"
  },
  {
    "id": 24485,
    "date": "2025-06-24 19:27:25+00:00",
    "sender_name": "bfcrazy",
    "text": "Ну само собой"
  },
  {
    "id": 24484,
    "date": "2025-06-24 19:27:25+00:00",
    "sender_name": "oppionme",
    "text": "схуяиле"
  },
  {
    "id": 24483,
    "date": "2025-06-24 19:27:18+00:00",
    "sender_name": "GeorgeKan",
    "text": "Самострел в хуй?"
  },
  {
    "id": 24482,
    "date": "2025-06-24 19:27:10+00:00",
    "sender_name": "bfcrazy",
    "text": "Ю"
  },
  {
    "id": 24481,
    "date": "2025-06-24 19:27:09+00:00",
    "sender_name": "bfcrazy",
    "text": "Боле"
  },
  {
    "id": 24480,
    "date": "2025-06-24 19:27:08+00:00",
    "sender_name": "bfcrazy",
    "text": "Типо бол"
  },
  {
    "id": 24479,
    "date": "2025-06-24 19:27:05+00:00",
    "sender_name": "bfcrazy",
    "text": "Я щас в госпитале отдыхаю"
  },
  {
    "id": 24478,
    "date": "2025-06-24 19:26:56+00:00",
    "sender_name": "oppionme",
    "text": "сделал уже"
  },
  {
    "id": 24477,
    "date": "2025-06-24 19:26:56+00:00",
    "sender_name": "bfcrazy",
    "text": "Ну мне нахуй особо не нужен он, мне главное чтобы номер перенёсся на новую симку чтобы все восстановить"
  },
  {
    "id": 24473,
    "date": "2025-06-24 19:26:40+00:00",
    "sender_name": "GeorgeKan",
    "text": "В грузии 12"
  },
  {
    "id": 24472,
    "date": "2025-06-24 19:26:26+00:00",
    "sender_name": "GeorgeKan",
    "text": "Вот и думайте"
  },
  {
    "id": 24471,
    "date": "2025-06-24 19:26:25+00:00",
    "sender_name": "bfcrazy",
    "text": "Вернут потом"
  },
  {
    "id": 24470,
    "date": "2025-06-24 19:26:24+00:00",
    "sender_name": "GeorgeKan",
    "text": "А в школе этим занимаются 11 лет"
  },
  {
    "id": 24465,
    "date": "2025-06-24 19:26:06+00:00",
    "sender_name": "bfcrazy",
    "text": "2 дня"
  },
  {
    "id": 24464,
    "date": "2025-06-24 19:26:04+00:00",
    "sender_name": "GeorgeKan",
    "text": "Пизды в армии никто не даст"
  },
  {
    "id": 24463,
    "date": "2025-06-24 19:26:03+00:00",
    "sender_name": "bfcrazy",
    "text": "Пидорил все нахуй ссаной тряпкой"
  },
  {
    "id": 24459,
    "date": "2025-06-24 19:25:52+00:00",
    "sender_name": "bfcrazy",
    "text": "Ну как пизды дали"
  },
  {
    "id": 24458,
    "date": "2025-06-24 19:25:40+00:00",
    "sender_name": "bfcrazy",
    "text": "Потому что 1 Жора уже спиздил"
  },
  {
    "id": 24457,
    "date": "2025-06-24 19:25:38+00:00",
    "sender_name": "oppionme",
    "text": "ты просто его знания не ведал"
  },
  {
    "id": 24455,
    "date": "2025-06-24 19:25:33+00:00",
    "sender_name": "bfcrazy",
    "text": "2+2=3"
  },
  {
    "id": 24451,
    "date": "2025-06-24 19:25:21+00:00",
    "sender_name": "bfcrazy",
    "text": "Нихуя"
  },
  {
    "id": 24450,
    "date": "2025-06-24 19:25:12+00:00",
    "sender_name": "oppionme",
    "text": "хпахпхвхв Женя лучше Тимофея школьную программу знает"
  },
  {
    "id": 24449,
    "date": "2025-06-24 19:25:11+00:00",
    "sender_name": "bfcrazy",
    "text": "Так да"
  },
  {
    "id": 24445,
    "date": "2025-06-24 19:25:03+00:00",
    "sender_name": "bfcrazy",
    "text": "Извини"
  },
  {
    "id": 24444,
    "date": "2025-06-24 19:25:00+00:00",
    "sender_name": "bfcrazy",
    "text": "Уже не водила я"
  },
  {
    "id": 24438,
    "date": "2025-06-24 19:24:42+00:00",
    "sender_name": "bfcrazy",
    "text": "Нихуя там не сложнее огэ"
  },
  {
    "id": 24437,
    "date": "2025-06-24 19:24:33+00:00",
    "sender_name": "bfcrazy",
    "text": "Я после 11 ушел еблуша"
  },
  {
    "id": 24435,
    "date": "2025-06-24 19:23:46+00:00",
    "sender_name": "GeorgeKan",
    "text": "Мне атестат дали по приколу"
  },
  {
    "id": 24433,
    "date": "2025-06-24 19:23:36+00:00",
    "sender_name": "GeorgeKan",
    "text": "Я нихкя не сдавал"
  },
  {
    "id": 24428,
    "date": "2025-06-24 19:20:07+00:00",
    "sender_name": "bfcrazy",
    "text": "Там за то что ФИО печатными буквами в рамках написал уже тройка"
  },
  {
    "id": 24427,
    "date": "2025-06-24 19:19:20+00:00",
    "sender_name": "GeorgeKan",
    "text": "Ты не справился с написантем своего имени?"
  },
  {
    "id": 24426,
    "date": "2025-06-24 19:19:00+00:00",
    "sender_name": "GeorgeKan",
    "text": "Дефолт путь нпс"
  },
  {
    "id": 24425,
    "date": "2025-06-24 19:18:55+00:00",
    "sender_name": "GeorgeKan",
    "text": "0 авантюризма"
  },
  {
    "id": 24411,
    "date": "2025-06-24 19:07:18+00:00",
    "sender_name": "bfcrazy",
    "text": "Потому что из мужской только другое выходит"
  },
  {
    "id": 24410,
    "date": "2025-06-24 19:06:52+00:00",
    "sender_name": "bfcrazy",
    "text": "Полагаю из женской пизды"
  },
  {
    "id": 24409,
    "date": "2025-06-24 18:58:28+00:00",
    "sender_name": "oppionme",
    "text": "бляди"
  },
  {
    "id": 24408,
    "date": "2025-06-24 18:58:26+00:00",
    "sender_name": "oppionme",
    "text": "180+"
  },
  {
    "id": 24407,
    "date": "2025-06-24 18:58:23+00:00",
    "sender_name": "oppionme",
    "text": "jnrelf"
  },
  {
    "id": 24406,
    "date": "2025-06-24 18:57:13+00:00",
    "sender_name": "bfcrazy",
    "text": "И не подавать команду общий сбор"
  },
  {
    "id": 24405,
    "date": "2025-06-24 18:56:58+00:00",
    "sender_name": "GeorgeKan",
    "text": "[ПНД](tg://user?id=7079963747) огромная просьба, если всё таки начнёшь дрочить, не оповещать всех участников"
  }
]